[
  {
    "id": "Q01",
    "dimension": "decisions",
    "text": "Как в компании обычно принимаются ключевые решения по новым задачам?",
    "options": [
      {
        "key": "A",
        "label": "Решает собственник сразу, без формального обсуждения.",
        "scores": {
          "Младенчество": 3,
          "Давай-давай": 2,
          "Юность": 1,
          "Расцвет": 0,
          "Стабильность": 0,
          "Аристократизм": 0,
          "Ранний бюрократизм": 0,
          "Бюрократия": 0
        }
      },
      {
        "key": "B",
        "label": "Собственник решает, но уже советуется с руководителями.",
        "scores": {
          "Младенчество": 0,
          "Давай-давай": 3,
          "Юность": 2,
          "Расцвет": 1,
          "Стабильность": 0,
          "Аристократизм": 0,
          "Ранний бюрократизм": 0,
          "Бюрократия": 0
        }
      },
      {
        "key": "C",
        "label": "Есть правила принятия решений и понятные критерии выбора.",
        "scores": {
          "Младенчество": 0,
          "Давай-давай": 1,
          "Юность": 2,
          "Расцвет": 3,
          "Стабильность": 2,
          "Аристократизм": 0,
          "Ранний бюрократизм": 0,
          "Бюрократия": 0
        }
      },
      {
        "key": "D",
        "label": "Решения идут через длинные согласования и часто теряют смысл.",
        "scores": {
          "Младенчество": 0,
          "Давай-давай": 0,
          "Юность": 0,
          "Расцвет": 0,
          "Стабильность": 1,
          "Аристократизм": 2,
          "Ранний бюрократизм": 3,
          "Бюрократия": 3
        }
      }
    ]
  },
  {
    "id": "Q02",
    "dimension": "decisions",
    "text": "Что чаще всего влияет на выбор приоритетов на месяц?",
    "options": [
      {
        "key": "A",
        "label": "Срочные запросы клиентов и личное мнение собственника.",
        "scores": {
          "Младенчество": 3,
          "Давай-давай": 2,
          "Юность": 1,
          "Расцвет": 0,
          "Стабильность": 0,
          "Аристократизм": 0,
          "Ранний бюрократизм": 0,
          "Бюрократия": 0
        }
      },
      {
        "key": "B",
        "label": "Компромисс между срочными задачами и планом руководителей.",
        "scores": {
          "Младенчество": 0,
          "Давай-давай": 3,
          "Юность": 2,
          "Расцвет": 1,
          "Стабильность": 0,
          "Аристократизм": 0,
          "Ранний бюрократизм": 0,
          "Бюрократия": 0
        }
      },
      {
        "key": "C",
        "label": "Приоритеты опираются на стратегию, цифры и ресурсный план.",
        "scores": {
          "Младенчество": 0,
          "Давай-давай": 1,
          "Юность": 2,
          "Расцвет": 3,
          "Стабильность": 2,
          "Аристократизм": 0,
          "Ранний бюрократизм": 0,
          "Бюрократия": 0
        }
      },
      {
        "key": "D",
        "label": "Приоритеты формально утверждаются, но реально не исполняются.",
        "scores": {
          "Младенчество": 0,
          "Давай-давай": 0,
          "Юность": 0,
          "Расцвет": 0,
          "Стабильность": 1,
          "Аристократизм": 2,
          "Ранний бюрократизм": 3,
          "Бюрократия": 3
        }
      }
    ]
  },
  {
    "id": "Q03",
    "dimension": "decisions",
    "text": "Как в компании разбирают ошибочные решения?",
    "options": [
      {
        "key": "A",
        "label": "Реагируем ситуативно, без фиксированных выводов.",
        "scores": {
          "Младенчество": 3,
          "Давай-давай": 2,
          "Юность": 1,
          "Расцвет": 0,
          "Стабильность": 0,
          "Аристократизм": 0,
          "Ранний бюрократизм": 0,
          "Бюрократия": 0
        }
      },
      {
        "key": "B",
        "label": "Периодически разбираем, но не всегда меняем подход.",
        "scores": {
          "Младенчество": 0,
          "Давай-давай": 3,
          "Юность": 2,
          "Расцвет": 1,
          "Стабильность": 0,
          "Аристократизм": 0,
          "Ранний бюрократизм": 0,
          "Бюрократия": 0
        }
      },
      {
        "key": "C",
        "label": "Есть регулярный разбор причин и корректировка правил.",
        "scores": {
          "Младенчество": 0,
          "Давай-давай": 1,
          "Юность": 2,
          "Расцвет": 3,
          "Стабильность": 2,
          "Аристократизм": 0,
          "Ранний бюрократизм": 0,
          "Бюрократия": 0
        }
      },
      {
        "key": "D",
        "label": "Главная цель разбора — найти виновного, а не улучшить систему.",
        "scores": {
          "Младенчество": 0,
          "Давай-давай": 0,
          "Юность": 0,
          "Расцвет": 0,
          "Стабильность": 1,
          "Аристократизм": 2,
          "Ранний бюрократизм": 3,
          "Бюрократия": 3
        }
      }
    ]
  },
  {
    "id": "Q04",
    "dimension": "processes",
    "text": "Как устроены ключевые процессы (продажи, исполнение, сервис)?",
    "options": [
      {
        "key": "A",
        "label": "Процессы в голове у людей, каждый работает по-своему.",
        "scores": {
          "Младенчество": 3,
          "Давай-давай": 2,
          "Юность": 1,
          "Расцвет": 0,
          "Стабильность": 0,
          "Аристократизм": 0,
          "Ранний бюрократизм": 0,
          "Бюрократия": 0
        }
      },
      {
        "key": "B",
        "label": "Есть базовые регламенты, но соблюдаются неравномерно.",
        "scores": {
          "Младенчество": 0,
          "Давай-давай": 3,
          "Юность": 2,
          "Расцвет": 1,
          "Стабильность": 0,
          "Аристократизм": 0,
          "Ранний бюрократизм": 0,
          "Бюрократия": 0
        }
      },
      {
        "key": "C",
        "label": "Процессы описаны, просты и дают предсказуемый результат.",
        "scores": {
          "Младенчество": 0,
          "Давай-давай": 1,
          "Юность": 2,
          "Расцвет": 3,
          "Стабильность": 2,
          "Аристократизм": 0,
          "Ранний бюрократизм": 0,
          "Бюрократия": 0
        }
      },
      {
        "key": "D",
        "label": "Регламентов много, но они тормозят работу и не помогают клиенту.",
        "scores": {
          "Младенчество": 0,
          "Давай-давай": 0,
          "Юность": 0,
          "Расцвет": 0,
          "Стабильность": 1,
          "Аристократизм": 2,
          "Ранний бюрократизм": 3,
          "Бюрократия": 3
        }
      }
    ]
  },
  {
    "id": "Q05",
    "dimension": "processes",
    "text": "Как обычно внедряются изменения в процессах?",
    "options": [
      {
        "key": "A",
        "label": "Меняем на ходу, без теста и фиксации новых правил.",
        "scores": {
          "Младенчество": 3,
          "Давай-давай": 2,
          "Юность": 1,
          "Расцвет": 0,
          "Стабильность": 0,
          "Аристократизм": 0,
          "Ранний бюрократизм": 0,
          "Бюрократия": 0
        }
      },
      {
        "key": "B",
        "label": "Изменения согласуются, но их внедрение зависит от энтузиазма команды.",
        "scores": {
          "Младенчество": 0,
          "Давай-давай": 3,
          "Юность": 2,
          "Расцвет": 1,
          "Стабильность": 0,
          "Аристократизм": 0,
          "Ранний бюрократизм": 0,
          "Бюрократия": 0
        }
      },
      {
        "key": "C",
        "label": "Есть порядок: пилот, измерение эффекта, масштабирование.",
        "scores": {
          "Младенчество": 0,
          "Давай-давай": 1,
          "Юность": 2,
          "Расцвет": 3,
          "Стабильность": 2,
          "Аристократизм": 0,
          "Ранний бюрократизм": 0,
          "Бюрократия": 0
        }
      },
      {
        "key": "D",
        "label": "Даже небольшие изменения проходят длинную формальную процедуру.",
        "scores": {
          "Младенчество": 0,
          "Давай-давай": 0,
          "Юность": 0,
          "Расцвет": 0,
          "Стабильность": 1,
          "Аристократизм": 2,
          "Ранний бюрократизм": 3,
          "Бюрократия": 3
        }
      }
    ]
  },
  {
    "id": "Q06",
    "dimension": "processes",
    "text": "Что лучше описывает контроль качества исполнения?",
    "options": [
      {
        "key": "A",
        "label": "Качество держится на личном контроле нескольких людей.",
        "scores": {
          "Младенчество": 3,
          "Давай-давай": 2,
          "Юность": 1,
          "Расцвет": 0,
          "Стабильность": 0,
          "Аристократизм": 0,
          "Ранний бюрократизм": 0,
          "Бюрократия": 0
        }
      },
      {
        "key": "B",
        "label": "Есть чек-листы, но стандарты часто трактуются по-разному.",
        "scores": {
          "Младенчество": 0,
          "Давай-давай": 3,
          "Юность": 2,
          "Расцвет": 1,
          "Стабильность": 0,
          "Аристократизм": 0,
          "Ранний бюрократизм": 0,
          "Бюрократия": 0
        }
      },
      {
        "key": "C",
        "label": "Критерии качества едины, метрики прозрачны, отклонения быстро исправляются.",
        "scores": {
          "Младенчество": 0,
          "Давай-давай": 1,
          "Юность": 2,
          "Расцвет": 3,
          "Стабильность": 2,
          "Аристократизм": 0,
          "Ранний бюрократизм": 0,
          "Бюрократия": 0
        }
      },
      {
        "key": "D",
        "label": "Отчетов о качестве много, а реальные улучшения редки.",
        "scores": {
          "Младенчество": 0,
          "Давай-давай": 0,
          "Юность": 0,
          "Расцвет": 0,
          "Стабильность": 1,
          "Аристократизм": 2,
          "Ранний бюрократизм": 3,
          "Бюрократия": 3
        }
      }
    ]
  },
  {
    "id": "Q07",
    "dimension": "owner_dependency",
    "text": "Что происходит, если собственник уезжает на две недели?",
    "options": [
      {
        "key": "A",
        "label": "Операционка заметно проседает, ключевые решения останавливаются.",
        "scores": {
          "Младенчество": 3,
          "Давай-давай": 2,
          "Юность": 1,
          "Расцвет": 0,
          "Стабильность": 0,
          "Аристократизм": 0,
          "Ранний бюрократизм": 0,
          "Бюрократия": 0
        }
      },
      {
        "key": "B",
        "label": "Команда тянет базу, но сложные вопросы ждут возвращения.",
        "scores": {
          "Младенчество": 0,
          "Давай-давай": 3,
          "Юность": 2,
          "Расцвет": 1,
          "Стабильность": 0,
          "Аристократизм": 0,
          "Ранний бюрократизм": 0,
          "Бюрократия": 0
        }
      },
      {
        "key": "C",
        "label": "Бизнес работает в штатном режиме по закрепленным полномочиям.",
        "scores": {
          "Младенчество": 0,
          "Давай-давай": 1,
          "Юность": 2,
          "Расцвет": 3,
          "Стабильность": 2,
          "Аристократизм": 0,
          "Ранний бюрократизм": 0,
          "Бюрократия": 0
        }
      },
      {
        "key": "D",
        "label": "Ничего не ускоряется: система и без собственника медленно двигается.",
        "scores": {
          "Младенчество": 0,
          "Давай-давай": 0,
          "Юность": 0,
          "Расцвет": 0,
          "Стабильность": 1,
          "Аристократизм": 2,
          "Ранний бюрократизм": 3,
          "Бюрократия": 3
        }
      }
    ]
  },
  {
    "id": "Q08",
    "dimension": "owner_dependency",
    "text": "Кто чаще принимает кадровые решения по руководителям?",
    "options": [
      {
        "key": "A",
        "label": "Почти всегда собственник, даже по операционным ролям.",
        "scores": {
          "Младенчество": 3,
          "Давай-давай": 2,
          "Юность": 1,
          "Расцвет": 0,
          "Стабильность": 0,
          "Аристократизм": 0,
          "Ранний бюрократизм": 0,
          "Бюрократия": 0
        }
      },
      {
        "key": "B",
        "label": "Руководители участвуют, но финальное слово у собственника.",
        "scores": {
          "Младенчество": 0,
          "Давай-давай": 3,
          "Юность": 2,
          "Расцвет": 1,
          "Стабильность": 0,
          "Аристократизм": 0,
          "Ранний бюрократизм": 0,
          "Бюрократия": 0
        }
      },
      {
        "key": "C",
        "label": "Есть понятный контур: решения принимаются на соответствующем уровне.",
        "scores": {
          "Младенчество": 0,
          "Давай-давай": 1,
          "Юность": 2,
          "Расцвет": 3,
          "Стабильность": 2,
          "Аристократизм": 0,
          "Ранний бюрократизм": 0,
          "Бюрократия": 0
        }
      },
      {
        "key": "D",
        "label": "Кадровые решения зависают между комитетами и регламентами.",
        "scores": {
          "Младенчество": 0,
          "Давай-давай": 0,
          "Юность": 0,
          "Расцвет": 0,
          "Стабильность": 1,
          "Аристократизм": 2,
          "Ранний бюрократизм": 3,
          "Бюрократия": 3
        }
      }
    ]
  },
  {
    "id": "Q09",
    "dimension": "owner_dependency",
    "text": "Как распределены внешние контакты с ключевыми клиентами и партнерами?",
    "options": [
      {
        "key": "A",
        "label": "Почти все держится на личных связях собственника.",
        "scores": {
          "Младенчество": 3,
          "Давай-давай": 2,
          "Юность": 1,
          "Расцвет": 0,
          "Стабильность": 0,
          "Аристократизм": 0,
          "Ранний бюрократизм": 0,
          "Бюрократия": 0
        }
      },
      {
        "key": "B",
        "label": "Часть контактов делегирована, но крупные вопросы решает собственник.",
        "scores": {
          "Младенчество": 0,
          "Давай-давай": 3,
          "Юность": 2,
          "Расцвет": 1,
          "Стабильность": 0,
          "Аристократизм": 0,
          "Ранний бюрократизм": 0,
          "Бюрократия": 0
        }
      },
      {
        "key": "C",
        "label": "Клиентский контур распределен по ролям, отношения устойчивы без ручного режима.",
        "scores": {
          "Младенчество": 0,
          "Давай-давай": 1,
          "Юность": 2,
          "Расцвет": 3,
          "Стабильность": 2,
          "Аристократизм": 0,
          "Ранний бюрократизм": 0,
          "Бюрократия": 0
        }
      },
      {
        "key": "D",
        "label": "Контакты формально распределены, но решения по клиентам движутся слишком долго.",
        "scores": {
          "Младенчество": 0,
          "Давай-давай": 0,
          "Юность": 0,
          "Расцвет": 0,
          "Стабильность": 1,
          "Аристократизм": 2,
          "Ранний бюрократизм": 3,
          "Бюрократия": 3
        }
      }
    ]
  },
  {
    "id": "Q10",
    "dimension": "kpi_contour",
    "text": "Как в компании устроена система KPI и регулярных управленческих встреч?",
    "options": [
      {
        "key": "A",
        "label": "Единых KPI нет, фокус на срочных задачах.",
        "scores": {
          "Младенчество": 3,
          "Давай-давай": 2,
          "Юность": 1,
          "Расцвет": 0,
          "Стабильность": 0,
          "Аристократизм": 0,
          "Ранний бюрократизм": 0,
          "Бюрократия": 0
        }
      },
      {
        "key": "B",
        "label": "KPI есть, но часть показателей не влияет на решения.",
        "scores": {
          "Младенчество": 0,
          "Давай-давай": 3,
          "Юность": 2,
          "Расцвет": 1,
          "Стабильность": 0,
          "Аристократизм": 0,
          "Ранний бюрократизм": 0,
          "Бюрократия": 0
        }
      },
      {
        "key": "C",
        "label": "Метрики связаны со стратегией, встречи приводят к конкретным действиям.",
        "scores": {
          "Младенчество": 0,
          "Давай-давай": 1,
          "Юность": 2,
          "Расцвет": 3,
          "Стабильность": 2,
          "Аристократизм": 0,
          "Ранний бюрократизм": 0,
          "Бюрократия": 0
        }
      },
      {
        "key": "D",
        "label": "Показателей много, но они живут отдельно от реального управления.",
        "scores": {
          "Младенчество": 0,
          "Давай-давай": 0,
          "Юность": 0,
          "Расцвет": 0,
          "Стабильность": 1,
          "Аристократизм": 2,
          "Ранний бюрократизм": 3,
          "Бюрократия": 3
        }
      }
    ]
  },
  {
    "id": "Q11",
    "dimension": "kpi_contour",
    "text": "Как команда работает с отклонениями плана от факта?",
    "options": [
      {
        "key": "A",
        "label": "Реакция эпизодическая, без системной корректировки.",
        "scores": {
          "Младенчество": 3,
          "Давай-давай": 2,
          "Юность": 1,
          "Расцвет": 0,
          "Стабильность": 0,
          "Аристократизм": 0,
          "Ранний бюрократизм": 0,
          "Бюрократия": 0
        }
      },
      {
        "key": "B",
        "label": "Отклонения обсуждаются, но меры часто запаздывают.",
        "scores": {
          "Младенчество": 0,
          "Давай-давай": 3,
          "Юность": 2,
          "Расцвет": 1,
          "Стабильность": 0,
          "Аристократизм": 0,
          "Ранний бюрократизм": 0,
          "Бюрократия": 0
        }
      },
      {
        "key": "C",
        "label": "Есть регулярный цикл: факт, анализ причин, корректирующие действия.",
        "scores": {
          "Младенчество": 0,
          "Давай-давай": 1,
          "Юность": 2,
          "Расцвет": 3,
          "Стабильность": 2,
          "Аристократизм": 0,
          "Ранний бюрократизм": 0,
          "Бюрократия": 0
        }
      },
      {
        "key": "D",
        "label": "Отклонения в основном объясняются формальными причинами без изменений.",
        "scores": {
          "Младенчество": 0,
          "Давай-давай": 0,
          "Юность": 0,
          "Расцвет": 0,
          "Стабильность": 1,
          "Аристократизм": 2,
          "Ранний бюрократизм": 3,
          "Бюрократия": 3
        }
      }
    ]
  },
  {
    "id": "Q12",
    "dimension": "kpi_contour",
    "text": "Насколько понятны цели компании для линейных команд?",
    "options": [
      {
        "key": "A",
        "label": "Цели передаются устно и меняются по ситуации.",
        "scores": {
          "Младенчество": 3,
          "Давай-давай": 2,
          "Юность": 1,
          "Расцвет": 0,
          "Стабильность": 0,
          "Аристократизм": 0,
          "Ранний бюрократизм": 0,
          "Бюрократия": 0
        }
      },
      {
        "key": "B",
        "label": "Цели формулируются, но связь с ежедневной работой не всегда ясна.",
        "scores": {
          "Младенчество": 0,
          "Давай-давай": 3,
          "Юность": 2,
          "Расцвет": 1,
          "Стабильность": 0,
          "Аристократизм": 0,
          "Ранний бюрократизм": 0,
          "Бюрократия": 0
        }
      },
      {
        "key": "C",
        "label": "Цели декомпозированы по уровням, сотрудники понимают вклад своей функции.",
        "scores": {
          "Младенчество": 0,
          "Давай-давай": 1,
          "Юность": 2,
          "Расцвет": 3,
          "Стабильность": 2,
          "Аристократизм": 0,
          "Ранний бюрократизм": 0,
          "Бюрократия": 0
        }
      },
      {
        "key": "D",
        "label": "Цели формально есть, но команды работают ради отчетности.",
        "scores": {
          "Младенчество": 0,
          "Давай-давай": 0,
          "Юность": 0,
          "Расцвет": 0,
          "Стабильность": 1,
          "Аристократизм": 2,
          "Ранний бюрократизм": 3,
          "Бюрократия": 3
        }
      }
    ]
  },
  {
    "id": "Q13",
    "dimension": "decision_speed",
    "text": "С какой скоростью проходят межфункциональные решения?",
    "options": [
      {
        "key": "A",
        "label": "Быстро, но за счет импровизации и последующих переделок.",
        "scores": {
          "Младенчество": 3,
          "Давай-давай": 2,
          "Юность": 1,
          "Расцвет": 0,
          "Стабильность": 0,
          "Аристократизм": 0,
          "Ранний бюрократизм": 0,
          "Бюрократия": 0
        }
      },
      {
        "key": "B",
        "label": "Скорость средняя: часть вопросов идет быстро, часть упирается в людей.",
        "scores": {
          "Младенчество": 0,
          "Давай-давай": 3,
          "Юность": 2,
          "Расцвет": 1,
          "Стабильность": 0,
          "Аристократизм": 0,
          "Ранний бюрократизм": 0,
          "Бюрократия": 0
        }
      },
      {
        "key": "C",
        "label": "Сроки решений предсказуемы, эскалация работает без потерь качества.",
        "scores": {
          "Младенчество": 0,
          "Давай-давай": 1,
          "Юность": 2,
          "Расцвет": 3,
          "Стабильность": 2,
          "Аристократизм": 0,
          "Ранний бюрократизм": 0,
          "Бюрократия": 0
        }
      },
      {
        "key": "D",
        "label": "Согласования длинные, скорость падает на каждом уровне.",
        "scores": {
          "Младенчество": 0,
          "Давай-давай": 0,
          "Юность": 0,
          "Расцвет": 0,
          "Стабильность": 1,
          "Аристократизм": 2,
          "Ранний бюрократизм": 3,
          "Бюрократия": 3
        }
      }
    ]
  },
  {
    "id": "Q14",
    "dimension": "decision_speed",
    "text": "Как часто «зависают» вопросы без владельца и срока?",
    "options": [
      {
        "key": "A",
        "label": "Часто, но их проталкивают в ручном режиме.",
        "scores": {
          "Младенчество": 3,
          "Давай-давай": 2,
          "Юность": 1,
          "Расцвет": 0,
          "Стабильность": 0,
          "Аристократизм": 0,
          "Ранний бюрократизм": 0,
          "Бюрократия": 0
        }
      },
      {
        "key": "B",
        "label": "Бывают регулярно, особенно между подразделениями.",
        "scores": {
          "Младенчество": 0,
          "Давай-давай": 3,
          "Юность": 2,
          "Расцвет": 1,
          "Стабильность": 0,
          "Аристократизм": 0,
          "Ранний бюрократизм": 0,
          "Бюрократия": 0
        }
      },
      {
        "key": "C",
        "label": "Редко: владелец, срок и критерий результата фиксируются сразу.",
        "scores": {
          "Младенчество": 0,
          "Давай-давай": 1,
          "Юность": 2,
          "Расцвет": 3,
          "Стабильность": 2,
          "Аристократизм": 0,
          "Ранний бюрократизм": 0,
          "Бюрократия": 0
        }
      },
      {
        "key": "D",
        "label": "Почти каждый вопрос проходит несколько кругов без движения.",
        "scores": {
          "Младенчество": 0,
          "Давай-давай": 0,
          "Юность": 0,
          "Расцвет": 0,
          "Стабильность": 1,
          "Аристократизм": 2,
          "Ранний бюрократизм": 3,
          "Бюрократия": 3
        }
      }
    ]
  },
  {
    "id": "Q15",
    "dimension": "decision_speed",
    "text": "Как компания ведет себя при внештатной ситуации у клиента?",
    "options": [
      {
        "key": "A",
        "label": "Реагируем мгновенно, но часто в ущерб другим обязательствам.",
        "scores": {
          "Младенчество": 3,
          "Давай-давай": 2,
          "Юность": 1,
          "Расцвет": 0,
          "Стабильность": 0,
          "Аристократизм": 0,
          "Ранний бюрократизм": 0,
          "Бюрократия": 0
        }
      },
      {
        "key": "B",
        "label": "Реакция есть, но координация между функциями нестабильна.",
        "scores": {
          "Младенчество": 0,
          "Давай-давай": 3,
          "Юность": 2,
          "Расцвет": 1,
          "Стабильность": 0,
          "Аристократизм": 0,
          "Ранний бюрократизм": 0,
          "Бюрократия": 0
        }
      },
      {
        "key": "C",
        "label": "Есть понятный протокол, решения принимаются быстро и по роли.",
        "scores": {
          "Младенчество": 0,
          "Давай-давай": 1,
          "Юность": 2,
          "Расцвет": 3,
          "Стабильность": 2,
          "Аристократизм": 0,
          "Ранний бюрократизм": 0,
          "Бюрократия": 0
        }
      },
      {
        "key": "D",
        "label": "Сначала идут формальные согласования, клиент ждет слишком долго.",
        "scores": {
          "Младенчество": 0,
          "Давай-давай": 0,
          "Юность": 0,
          "Расцвет": 0,
          "Стабильность": 1,
          "Аристократизм": 2,
          "Ранний бюрократизм": 3,
          "Бюрократия": 3
        }
      }
    ]
  },
  {
    "id": "Q16",
    "dimension": "roles_conflicts",
    "text": "Насколько в компании понятны роли и границы ответственности?",
    "options": [
      {
        "key": "A",
        "label": "Роли плавающие, задачи распределяются по принципу «кто свободен».",
        "scores": {
          "Младенчество": 3,
          "Давай-давай": 2,
          "Юность": 1,
          "Расцвет": 0,
          "Стабильность": 0,
          "Аристократизм": 0,
          "Ранний бюрократизм": 0,
          "Бюрократия": 0
        }
      },
      {
        "key": "B",
        "label": "Роли обозначены, но пересечения вызывают регулярные споры.",
        "scores": {
          "Младенчество": 0,
          "Давай-давай": 3,
          "Юность": 2,
          "Расцвет": 1,
          "Стабильность": 0,
          "Аристократизм": 0,
          "Ранний бюрократизм": 0,
          "Бюрократия": 0
        }
      },
      {
        "key": "C",
        "label": "Зоны ответственности прозрачны, пересечения решаются рабочим порядком.",
        "scores": {
          "Младенчество": 0,
          "Давай-давай": 1,
          "Юность": 2,
          "Расцвет": 3,
          "Стабильность": 2,
          "Аристократизм": 0,
          "Ранний бюрократизм": 0,
          "Бюрократия": 0
        }
      },
      {
        "key": "D",
        "label": "Функции жестко разделены, совместные задачи тонут в согласованиях.",
        "scores": {
          "Младенчество": 0,
          "Давай-давай": 0,
          "Юность": 0,
          "Расцвет": 0,
          "Стабильность": 1,
          "Аристократизм": 2,
          "Ранний бюрократизм": 3,
          "Бюрократия": 3
        }
      }
    ]
  },
  {
    "id": "Q17",
    "dimension": "roles_conflicts",
    "text": "Как обычно решаются конфликты между отделами?",
    "options": [
      {
        "key": "A",
        "label": "Через вмешательство собственника в ручном режиме.",
        "scores": {
          "Младенчество": 3,
          "Давай-давай": 2,
          "Юность": 1,
          "Расцвет": 0,
          "Стабильность": 0,
          "Аристократизм": 0,
          "Ранний бюрократизм": 0,
          "Бюрократия": 0
        }
      },
      {
        "key": "B",
        "label": "Через руководителей, но правила урегулирования применяются не всегда.",
        "scores": {
          "Младенчество": 0,
          "Давай-давай": 3,
          "Юность": 2,
          "Расцвет": 1,
          "Стабильность": 0,
          "Аристократизм": 0,
          "Ранний бюрократизм": 0,
          "Бюрократия": 0
        }
      },
      {
        "key": "C",
        "label": "Есть понятный механизм эскалации и ответственность за итог.",
        "scores": {
          "Младенчество": 0,
          "Давай-давай": 1,
          "Юность": 2,
          "Расцвет": 3,
          "Стабильность": 2,
          "Аристократизм": 0,
          "Ранний бюрократизм": 0,
          "Бюрократия": 0
        }
      },
      {
        "key": "D",
        "label": "Конфликты уходят в переписку и формальные процедуры без результата.",
        "scores": {
          "Младенчество": 0,
          "Давай-давай": 0,
          "Юность": 0,
          "Расцвет": 0,
          "Стабильность": 1,
          "Аристократизм": 2,
          "Ранний бюрократизм": 3,
          "Бюрократия": 3
        }
      }
    ]
  },
  {
    "id": "Q18",
    "dimension": "roles_conflicts",
    "text": "Как распределены полномочия в управленческой команде?",
    "options": [
      {
        "key": "A",
        "label": "Формально полномочия есть, фактически ключевые решения централизованы.",
        "scores": {
          "Младенчество": 3,
          "Давай-давай": 2,
          "Юность": 1,
          "Расцвет": 0,
          "Стабильность": 0,
          "Аристократизм": 0,
          "Ранний бюрократизм": 0,
          "Бюрократия": 0
        }
      },
      {
        "key": "B",
        "label": "Полномочия частично делегированы, но рамки еще часто пересматриваются.",
        "scores": {
          "Младенчество": 0,
          "Давай-давай": 3,
          "Юность": 2,
          "Расцвет": 1,
          "Стабильность": 0,
          "Аристократизм": 0,
          "Ранний бюрократизм": 0,
          "Бюрократия": 0
        }
      },
      {
        "key": "C",
        "label": "Полномочия и лимиты решений зафиксированы и соблюдаются.",
        "scores": {
          "Младенчество": 0,
          "Давай-давай": 1,
          "Юность": 2,
          "Расцвет": 3,
          "Стабильность": 2,
          "Аристократизм": 0,
          "Ранний бюрократизм": 0,
          "Бюрократия": 0
        }
      },
      {
        "key": "D",
        "label": "Полномочия распылены, решения блокируются взаимными ограничениями.",
        "scores": {
          "Младенчество": 0,
          "Давай-давай": 0,
          "Юность": 0,
          "Расцвет": 0,
          "Стабильность": 1,
          "Аристократизм": 2,
          "Ранний бюрократизм": 3,
          "Бюрократия": 3
        }
      }
    ]
  },
  {
    "id": "Q19",
    "dimension": "growth_sustainability",
    "text": "Как выглядит рост бизнеса за последние 12 месяцев?",
    "options": [
      {
        "key": "A",
        "label": "Рост рывками, сильно зависит от отдельных сделок и людей.",
        "scores": {
          "Младенчество": 3,
          "Давай-давай": 2,
          "Юность": 1,
          "Расцвет": 0,
          "Стабильность": 0,
          "Аристократизм": 0,
          "Ранний бюрократизм": 0,
          "Бюрократия": 0
        }
      },
      {
        "key": "B",
        "label": "Рост есть, но его качество неравномерно по продуктам и командам.",
        "scores": {
          "Младенчество": 0,
          "Давай-давай": 3,
          "Юность": 2,
          "Расцвет": 1,
          "Стабильность": 0,
          "Аристократизм": 0,
          "Ранний бюрократизм": 0,
          "Бюрократия": 0
        }
      },
      {
        "key": "C",
        "label": "Рост управляемый: сохраняются маржа, качество и операционная устойчивость.",
        "scores": {
          "Младенчество": 0,
          "Давай-давай": 1,
          "Юность": 2,
          "Расцвет": 3,
          "Стабильность": 2,
          "Аристократизм": 0,
          "Ранний бюрократизм": 0,
          "Бюрократия": 0
        }
      },
      {
        "key": "D",
        "label": "Рост слабый или отрицательный, фокус смещен на сохранение формы.",
        "scores": {
          "Младенчество": 0,
          "Давай-давай": 0,
          "Юность": 0,
          "Расцвет": 0,
          "Стабильность": 1,
          "Аристократизм": 2,
          "Ранний бюрократизм": 3,
          "Бюрократия": 3
        }
      }
    ]
  },
  {
    "id": "Q20",
    "dimension": "growth_sustainability",
    "text": "Как компания балансирует текущую прибыль и развитие новых направлений?",
    "options": [
      {
        "key": "A",
        "label": "Развитие несистемное: запускаем идеи без ресурсного расчета.",
        "scores": {
          "Младенчество": 3,
          "Давай-давай": 2,
          "Юность": 1,
          "Расцвет": 0,
          "Стабильность": 0,
          "Аристократизм": 0,
          "Ранний бюрократизм": 0,
          "Бюрократия": 0
        }
      },
      {
        "key": "B",
        "label": "Есть попытки портфельного подхода, но дисциплина еще формируется.",
        "scores": {
          "Младенчество": 0,
          "Давай-давай": 3,
          "Юность": 2,
          "Расцвет": 1,
          "Стабильность": 0,
          "Аристократизм": 0,
          "Ранний бюрократизм": 0,
          "Бюрократия": 0
        }
      },
      {
        "key": "C",
        "label": "Баланс формализован: ядро приносит прибыль, развитие имеет отдельный контур.",
        "scores": {
          "Младенчество": 0,
          "Давай-давай": 1,
          "Юность": 2,
          "Расцвет": 3,
          "Стабильность": 2,
          "Аристократизм": 0,
          "Ранний бюрократизм": 0,
          "Бюрократия": 0
        }
      },
      {
        "key": "D",
        "label": "Развитие почти остановлено, приоритет — сохранение текущих правил.",
        "scores": {
          "Младенчество": 0,
          "Давай-давай": 0,
          "Юность": 0,
          "Расцвет": 0,
          "Стабильность": 1,
          "Аристократизм": 2,
          "Ранний бюрократизм": 3,
          "Бюрократия": 3
        }
      }
    ]
  },
  {
    "id": "Q21",
    "dimension": "growth_sustainability",
    "text": "Как бизнес реагирует на изменения рынка и конкурентов?",
    "options": [
      {
        "key": "A",
        "label": "Реагируем резко и точечно, без устойчивого плана.",
        "scores": {
          "Младенчество": 3,
          "Давай-давай": 2,
          "Юность": 1,
          "Расцвет": 0,
          "Стабильность": 0,
          "Аристократизм": 0,
          "Ранний бюрократизм": 0,
          "Бюрократия": 0
        }
      },
      {
        "key": "B",
        "label": "Реакция есть, но скорость и координация зависят от конкретных людей.",
        "scores": {
          "Младенчество": 0,
          "Давай-давай": 3,
          "Юность": 2,
          "Расцвет": 1,
          "Стабильность": 0,
          "Аристократизм": 0,
          "Ранний бюрократизм": 0,
          "Бюрократия": 0
        }
      },
      {
        "key": "C",
        "label": "Изменения отслеживаются регулярно, решения принимаются в рамках стратегии.",
        "scores": {
          "Младенчество": 0,
          "Давай-давай": 1,
          "Юность": 2,
          "Расцвет": 3,
          "Стабильность": 2,
          "Аристократизм": 0,
          "Ранний бюрократизм": 0,
          "Бюрократия": 0
        }
      },
      {
        "key": "D",
        "label": "Рынок меняется быстрее, чем внутренние решения компании.",
        "scores": {
          "Младенчество": 0,
          "Давай-давай": 0,
          "Юность": 0,
          "Расцвет": 0,
          "Стабильность": 1,
          "Аристократизм": 2,
          "Ранний бюрократизм": 3,
          "Бюрократия": 3
        }
      }
    ]
  },
  {
    "id": "Q22",
    "dimension": "finance_predictability",
    "text": "Насколько предсказуем денежный поток компании?",
    "options": [
      {
        "key": "A",
        "label": "Кассовые разрывы случаются часто, прогнозы приблизительные.",
        "scores": {
          "Младенчество": 3,
          "Давай-давай": 2,
          "Юность": 1,
          "Расцвет": 0,
          "Стабильность": 0,
          "Аристократизм": 0,
          "Ранний бюрократизм": 0,
          "Бюрократия": 0
        }
      },
      {
        "key": "B",
        "label": "Прогноз есть, но точность сильно зависит от менеджеров и сезонности.",
        "scores": {
          "Младенчество": 0,
          "Давай-давай": 3,
          "Юность": 2,
          "Расцвет": 1,
          "Стабильность": 0,
          "Аристократизм": 0,
          "Ранний бюрократизм": 0,
          "Бюрократия": 0
        }
      },
      {
        "key": "C",
        "label": "Платежный календарь и прогноз cash flow точны и регулярно обновляются.",
        "scores": {
          "Младенчество": 0,
          "Давай-давай": 1,
          "Юность": 2,
          "Расцвет": 3,
          "Стабильность": 2,
          "Аристократизм": 0,
          "Ранний бюрократизм": 0,
          "Бюрократия": 0
        }
      },
      {
        "key": "D",
        "label": "Финансовые данные есть, но они запаздывают и плохо помогают управлять.",
        "scores": {
          "Младенчество": 0,
          "Давай-давай": 0,
          "Юность": 0,
          "Расцвет": 0,
          "Стабильность": 1,
          "Аристократизм": 2,
          "Ранний бюрократизм": 3,
          "Бюрократия": 3
        }
      }
    ]
  },
  {
    "id": "Q23",
    "dimension": "finance_predictability",
    "text": "Как в компании принимаются решения по затратам?",
    "options": [
      {
        "key": "A",
        "label": "Затраты утверждаются по ситуации, без общей модели рентабельности.",
        "scores": {
          "Младенчество": 3,
          "Давай-давай": 2,
          "Юность": 1,
          "Расцвет": 0,
          "Стабильность": 0,
          "Аристократизм": 0,
          "Ранний бюрократизм": 0,
          "Бюрократия": 0
        }
      },
      {
        "key": "B",
        "label": "Бюджет есть, но управленческий учет не всегда поддерживает решения.",
        "scores": {
          "Младенчество": 0,
          "Давай-давай": 3,
          "Юность": 2,
          "Расцвет": 1,
          "Стабильность": 0,
          "Аристократизм": 0,
          "Ранний бюрократизм": 0,
          "Бюрократия": 0
        }
      },
      {
        "key": "C",
        "label": "Затраты управляются через бюджет, юнит-экономику и приоритеты роста.",
        "scores": {
          "Младенчество": 0,
          "Давай-давай": 1,
          "Юность": 2,
          "Расцвет": 3,
          "Стабильность": 2,
          "Аристократизм": 0,
          "Ранний бюрократизм": 0,
          "Бюрократия": 0
        }
      },
      {
        "key": "D",
        "label": "Контроль затрат формальный: экономят на развитии, не решая системных проблем.",
        "scores": {
          "Младенчество": 0,
          "Давай-давай": 0,
          "Юность": 0,
          "Расцвет": 0,
          "Стабильность": 1,
          "Аристократизм": 2,
          "Ранний бюрократизм": 3,
          "Бюрократия": 3
        }
      }
    ]
  },
  {
    "id": "Q24",
    "dimension": "finance_predictability",
    "text": "Как руководство видит финансовый результат по направлениям бизнеса?",
    "options": [
      {
        "key": "A",
        "label": "По направлениям прозрачности мало, смотрим в основном общую выручку.",
        "scores": {
          "Младенчество": 3,
          "Давай-давай": 2,
          "Юность": 1,
          "Расцвет": 0,
          "Стабильность": 0,
          "Аристократизм": 0,
          "Ранний бюрократизм": 0,
          "Бюрократия": 0
        }
      },
      {
        "key": "B",
        "label": "Разрезы есть, но методика и данные между отделами расходятся.",
        "scores": {
          "Младенчество": 0,
          "Давай-давай": 3,
          "Юность": 2,
          "Расцвет": 1,
          "Стабильность": 0,
          "Аристократизм": 0,
          "Ранний бюрократизм": 0,
          "Бюрократия": 0
        }
      },
      {
        "key": "C",
        "label": "P&L по направлениям регулярный и используется в управленческих решениях.",
        "scores": {
          "Младенчество": 0,
          "Давай-давай": 1,
          "Юность": 2,
          "Расцвет": 3,
          "Стабильность": 2,
          "Аристократизм": 0,
          "Ранний бюрократизм": 0,
          "Бюрократия": 0
        }
      },
      {
        "key": "D",
        "label": "Отчеты перегружены, но не дают ясной картины по эффективности направлений.",
        "scores": {
          "Младенчество": 0,
          "Давай-давай": 0,
          "Юность": 0,
          "Расцвет": 0,
          "Стабильность": 1,
          "Аристократизм": 2,
          "Ранний бюрократизм": 3,
          "Бюрократия": 3
        }
      }
    ]
  }
]
